forecast_order/__init__.py
forecast_order/forecast_order.py
forecast_order-0.1.1.dist-info/LICENSE
forecast_order-0.1.1.dist-info/METADATA
forecast_order-0.1.1.dist-info/WHEEL
forecast_order-0.1.1.dist-info/top_level.txt
forecast_order-0.1.1.dist-info/RECORD
