Metadata-Version: 2.1
Name: forecast_order
Version: 0.1.1
Summary: A package for forecasting orders using Hawk API.
Home-page: https://github.com/zenk-github/forecast_order
Author: Yuto Sasa
Author-email: y_sasa@zenk.co.jp
License: MIT
Classifier: Programming Language :: Python :: 3
Classifier: License :: OSI Approved :: MIT License
Classifier: Operating System :: OS Independent
License-File: LICENSE
Requires-Dist: requests
